kcp_net/__init__.py
kcp_net/connection.py
kcp_net/constants.py
kcp_net/log.py
kcp_net/mixins.py
kcp_net/output_listener.py
kcp_net/server.py
kcp_net/timer.py
kcp_net/utils.py
kcp_net-0.2.4.dist-info/METADATA
kcp_net-0.2.4.dist-info/WHEEL
kcp_net-0.2.4.dist-info/top_level.txt
kcp_net-0.2.4.dist-info/RECORD
