Metadata-Version: 2.1
Name: kcp-net
Version: 0.2.4
Summary: kcp_net
Home-page: https://github.com/dantezhu/kcp_net
Author: dantezhu
Author-email: dantezhu <zny2008@gmail.com>
License: MIT
Project-URL: Homepage, https://github.com/dantezhu/kcp_net
Platform: any
Requires-Dist: gevent
Requires-Dist: events
Requires-Dist: kcp-wrapper
